my_test_package/__init__.py
my_test_package/data_api_class.py
my_test_package/dict_data.py
my_test_package/dolphin_db_info.py
my_test_gj_package-0.0.3.dist-info/METADATA
my_test_gj_package-0.0.3.dist-info/WHEEL
my_test_gj_package-0.0.3.dist-info/top_level.txt
my_test_gj_package-0.0.3.dist-info/RECORD
