Metadata-Version: 2.1
Name: my-test-gj-package
Version: 0.0.3
Summary: 测试包1
Home-page: UNKNOWN
Author: yin
Author-email: 2018209921@qq.com
License: UNKNOWN
Platform: UNKNOWN
Requires-Python: >3.6
Requires-Dist: dolphindb ==3.0.1.0
Requires-Dist: holidays ==0.53
Requires-Dist: numpy ==1.26.3
Requires-Dist: pandas ==2.2.0
